test/__init__.py
test/test_config.py
wxconfig/__init__.py
wxconfig/config.py
wxconfig/wxconfiggui.py
wxconfig-1.5.dist-info/LICENSE
wxconfig-1.5.dist-info/METADATA
wxconfig-1.5.dist-info/WHEEL
wxconfig-1.5.dist-info/top_level.txt
wxconfig-1.5.dist-info/RECORD
