Metadata-Version: 2.1
Name: wxconfig
Version: 1.5
Summary: A package for managing application config through yaml files. Provides dynamically generated wxpython dialog.
Home-page: https://github.com/jamiecash/wxconfig
Author: Jamie Cash
Author-email: jlcash@gmail.com
License: UNKNOWN
Project-URL: Issue Tracker, https://github.com/jamiecash/wxconfig/issues
Platform: UNKNOWN
Classifier: Development Status :: 5 - Production/Stable
Classifier: Intended Audience :: Developers
Classifier: Topic :: Software Development :: Build Tools
Classifier: License :: OSI Approved :: MIT License
Classifier: Operating System :: OS Independent
Classifier: Programming Language :: Python :: 3.6
Classifier: Programming Language :: Python :: 3.7
Classifier: Programming Language :: Python :: 3.8
Classifier: Programming Language :: Python :: 3.9
Requires-Python: >=3.6
License-File: LICENSE
Requires-Dist: wxpython (==4.1.1)
Requires-Dist: pyyaml (==5.4.1)
